<?xml version="1.0" encoding="UTF-8"?>
<!-- generated on 2020-04-22 22:55:44.303186 by training_main.py v1_5_0+0000-3a3be608d2
  options: 
-->
<routes xmlns:xsi="http://www.w3.org/2001/XMLSchema-instance" xsi:noNamespaceSchemaLocation="http://sumo.dlr.de/xsd/routes_file.xsd">
    <person id="ped0" depart="46.00" departPos="random">
        <walk from="NC" to="CS" arrivalPos="random"/>
    </person>
    <person id="ped1" depart="59.00" departPos="random">
        <walk from="CS" to="NC" arrivalPos="random"/>
    </person>
    <person id="ped2" depart="72.00" departPos="random">
        <walk from="CS" to="NC" arrivalPos="random"/>
    </person>
    <person id="ped3" depart="102.00" departPos="random">
        <walk from="CS" to="NC" arrivalPos="random"/>
    </person>
    <person id="ped4" depart="127.00" departPos="random">
        <walk from="CS" to="NC" arrivalPos="random"/>
    </person>
    <person id="ped5" depart="141.00" departPos="random">
        <walk from="CS" to="NC" arrivalPos="random"/>
    </person>
    <person id="ped6" depart="152.00" departPos="random">
        <walk from="CS" to="NC" arrivalPos="random"/>
    </person>
    <person id="ped7" depart="224.00" departPos="random">
        <walk from="CS" to="NC" arrivalPos="random"/>
    </person>
    <person id="ped8" depart="326.00" departPos="random">
        <walk from="CS" to="NC" arrivalPos="random"/>
    </person>
    <person id="ped9" depart="327.00" departPos="random">
        <walk from="CS" to="NC" arrivalPos="random"/>
    </person>
    <person id="ped10" depart="342.00" departPos="random">
        <walk from="NC" to="CS" arrivalPos="random"/>
    </person>
    <person id="ped11" depart="348.00" departPos="random">
        <walk from="CS" to="NC" arrivalPos="random"/>
    </person>
    <person id="ped12" depart="416.00" departPos="random">
        <walk from="NC" to="CS" arrivalPos="random"/>
    </person>
    <person id="ped13" depart="418.00" departPos="random">
        <walk from="CS" to="NC" arrivalPos="random"/>
    </person>
    <person id="ped14" depart="421.00" departPos="random">
        <walk from="CS" to="NC" arrivalPos="random"/>
    </person>
    <person id="ped15" depart="435.00" departPos="random">
        <walk from="NC" to="CS" arrivalPos="random"/>
    </person>
    <person id="ped16" depart="461.00" departPos="random">
        <walk from="NC" to="CS" arrivalPos="random"/>
    </person>
    <person id="ped17" depart="494.00" departPos="random">
        <walk from="CS" to="NC" arrivalPos="random"/>
    </person>
    <person id="ped18" depart="506.00" departPos="random">
        <walk from="NC" to="CS" arrivalPos="random"/>
    </person>
    <person id="ped19" depart="585.00" departPos="random">
        <walk from="NC" to="CS" arrivalPos="random"/>
    </person>
    <person id="ped20" depart="601.00" departPos="random">
        <walk from="NC" to="CS" arrivalPos="random"/>
    </person>
    <person id="ped21" depart="613.00" departPos="random">
        <walk from="NC" to="CS" arrivalPos="random"/>
    </person>
    <person id="ped22" depart="656.00" departPos="random">
        <walk from="CS" to="NC" arrivalPos="random"/>
    </person>
    <person id="ped23" depart="706.00" departPos="random">
        <walk from="NC" to="CS" arrivalPos="random"/>
    </person>
    <person id="ped24" depart="724.00" departPos="random">
        <walk from="NC" to="CS" arrivalPos="random"/>
    </person>
    <person id="ped25" depart="741.00" departPos="random">
        <walk from="NC" to="CS" arrivalPos="random"/>
    </person>
    <person id="ped26" depart="760.00" departPos="random">
        <walk from="CS" to="NC" arrivalPos="random"/>
    </person>
    <person id="ped27" depart="811.00" departPos="random">
        <walk from="NC" to="CS" arrivalPos="random"/>
    </person>
    <person id="ped28" depart="823.00" departPos="random">
        <walk from="CS" to="NC" arrivalPos="random"/>
    </person>
    <person id="ped29" depart="832.00" departPos="random">
        <walk from="CS" to="NC" arrivalPos="random"/>
    </person>
    <person id="ped30" depart="876.00" departPos="random">
        <walk from="CS" to="NC" arrivalPos="random"/>
    </person>
    <person id="ped31" depart="954.00" departPos="random">
        <walk from="CS" to="NC" arrivalPos="random"/>
    </person>
    <person id="ped32" depart="955.00" departPos="random">
        <walk from="CS" to="NC" arrivalPos="random"/>
    </person>
    <person id="ped33" depart="999.00" departPos="random">
        <walk from="NC" to="CS" arrivalPos="random"/>
    </person>
    <person id="ped34" depart="1127.00" departPos="random">
        <walk from="NC" to="CS" arrivalPos="random"/>
    </person>
    <person id="ped35" depart="1160.00" departPos="random">
        <walk from="CS" to="NC" arrivalPos="random"/>
    </person>
    <person id="ped36" depart="1231.00" departPos="random">
        <walk from="NC" to="CS" arrivalPos="random"/>
    </person>
    <person id="ped37" depart="1292.00" departPos="random">
        <walk from="NC" to="CS" arrivalPos="random"/>
    </person>
    <person id="ped38" depart="1340.00" departPos="random">
        <walk from="NC" to="CS" arrivalPos="random"/>
    </person>
    <person id="ped39" depart="1344.00" departPos="random">
        <walk from="NC" to="CS" arrivalPos="random"/>
    </person>
    <person id="ped40" depart="1357.00" departPos="random">
        <walk from="NC" to="CS" arrivalPos="random"/>
    </person>
    <person id="ped41" depart="1373.00" departPos="random">
        <walk from="NC" to="CS" arrivalPos="random"/>
    </person>
    <person id="ped42" depart="1468.00" departPos="random">
        <walk from="NC" to="CS" arrivalPos="random"/>
    </person>
    <person id="ped43" depart="1472.00" departPos="random">
        <walk from="CS" to="NC" arrivalPos="random"/>
    </person>
    <person id="ped44" depart="1505.00" departPos="random">
        <walk from="CS" to="NC" arrivalPos="random"/>
    </person>
    <person id="ped45" depart="1520.00" departPos="random">
        <walk from="CS" to="NC" arrivalPos="random"/>
    </person>
    <person id="ped46" depart="1593.00" departPos="random">
        <walk from="CS" to="NC" arrivalPos="random"/>
    </person>
    <person id="ped47" depart="1604.00" departPos="random">
        <walk from="CS" to="NC" arrivalPos="random"/>
    </person>
    <person id="ped48" depart="1633.00" departPos="random">
        <walk from="NC" to="CS" arrivalPos="random"/>
    </person>
    <person id="ped49" depart="1658.00" departPos="random">
        <walk from="CS" to="NC" arrivalPos="random"/>
    </person>
    <person id="ped50" depart="1747.00" departPos="random">
        <walk from="CS" to="NC" arrivalPos="random"/>
    </person>
    <person id="ped51" depart="1766.00" departPos="random">
        <walk from="NC" to="CS" arrivalPos="random"/>
    </person>
    <person id="ped52" depart="1830.00" departPos="random">
        <walk from="NC" to="CS" arrivalPos="random"/>
    </person>
    <person id="ped53" depart="1857.00" departPos="random">
        <walk from="NC" to="CS" arrivalPos="random"/>
    </person>
    <person id="ped54" depart="1924.00" departPos="random">
        <walk from="NC" to="CS" arrivalPos="random"/>
    </person>
    <person id="ped55" depart="1976.00" departPos="random">
        <walk from="CS" to="NC" arrivalPos="random"/>
    </person>
    <person id="ped56" depart="2038.00" departPos="random">
        <walk from="CS" to="NC" arrivalPos="random"/>
    </person>
    <person id="ped57" depart="2050.00" departPos="random">
        <walk from="NC" to="CS" arrivalPos="random"/>
    </person>
    <person id="ped58" depart="2085.00" departPos="random">
        <walk from="NC" to="CS" arrivalPos="random"/>
    </person>
    <person id="ped59" depart="2111.00" departPos="random">
        <walk from="NC" to="CS" arrivalPos="random"/>
    </person>
    <person id="ped60" depart="2205.00" departPos="random">
        <walk from="CS" to="NC" arrivalPos="random"/>
    </person>
    <person id="ped61" depart="2239.00" departPos="random">
        <walk from="CS" to="NC" arrivalPos="random"/>
    </person>
    <person id="ped62" depart="2263.00" departPos="random">
        <walk from="NC" to="CS" arrivalPos="random"/>
    </person>
    <person id="ped63" depart="2267.00" departPos="random">
        <walk from="NC" to="CS" arrivalPos="random"/>
    </person>
    <person id="ped64" depart="2291.00" departPos="random">
        <walk from="NC" to="CS" arrivalPos="random"/>
    </person>
    <person id="ped65" depart="2299.00" departPos="random">
        <walk from="CS" to="NC" arrivalPos="random"/>
    </person>
    <person id="ped66" depart="2329.00" departPos="random">
        <walk from="NC" to="CS" arrivalPos="random"/>
    </person>
    <person id="ped67" depart="2355.00" departPos="random">
        <walk from="NC" to="CS" arrivalPos="random"/>
    </person>
    <person id="ped68" depart="2377.00" departPos="random">
        <walk from="CS" to="NC" arrivalPos="random"/>
    </person>
    <person id="ped69" depart="2409.00" departPos="random">
        <walk from="CS" to="NC" arrivalPos="random"/>
    </person>
    <person id="ped70" depart="2415.00" departPos="random">
        <walk from="CS" to="NC" arrivalPos="random"/>
    </person>
    <person id="ped71" depart="2419.00" departPos="random">
        <walk from="CS" to="NC" arrivalPos="random"/>
    </person>
    <person id="ped72" depart="2420.00" departPos="random">
        <walk from="CS" to="NC" arrivalPos="random"/>
    </person>
    <person id="ped73" depart="2427.00" departPos="random">
        <walk from="NC" to="CS" arrivalPos="random"/>
    </person>
    <person id="ped74" depart="2444.00" departPos="random">
        <walk from="CS" to="NC" arrivalPos="random"/>
    </person>
    <person id="ped75" depart="2456.00" departPos="random">
        <walk from="NC" to="CS" arrivalPos="random"/>
    </person>
    <person id="ped76" depart="2456.00" departPos="random">
        <walk from="CS" to="NC" arrivalPos="random"/>
    </person>
    <person id="ped77" depart="2481.00" departPos="random">
        <walk from="NC" to="CS" arrivalPos="random"/>
    </person>
    <person id="ped78" depart="2488.00" departPos="random">
        <walk from="CS" to="NC" arrivalPos="random"/>
    </person>
    <person id="ped79" depart="2500.00" departPos="random">
        <walk from="NC" to="CS" arrivalPos="random"/>
    </person>
    <person id="ped80" depart="2500.00" departPos="random">
        <walk from="CS" to="NC" arrivalPos="random"/>
    </person>
    <person id="ped81" depart="2514.00" departPos="random">
        <walk from="NC" to="CS" arrivalPos="random"/>
    </person>
    <person id="ped82" depart="2514.00" departPos="random">
        <walk from="NC" to="CS" arrivalPos="random"/>
    </person>
    <person id="ped83" depart="2522.00" departPos="random">
        <walk from="NC" to="CS" arrivalPos="random"/>
    </person>
    <person id="ped84" depart="2581.00" departPos="random">
        <walk from="NC" to="CS" arrivalPos="random"/>
    </person>
    <person id="ped85" depart="2598.00" departPos="random">
        <walk from="CS" to="NC" arrivalPos="random"/>
    </person>
    <person id="ped86" depart="2607.00" departPos="random">
        <walk from="CS" to="NC" arrivalPos="random"/>
    </person>
    <person id="ped87" depart="2647.00" departPos="random">
        <walk from="NC" to="CS" arrivalPos="random"/>
    </person>
    <person id="ped88" depart="2773.00" departPos="random">
        <walk from="NC" to="CS" arrivalPos="random"/>
    </person>
    <person id="ped89" depart="2775.00" departPos="random">
        <walk from="NC" to="CS" arrivalPos="random"/>
    </person>
    <person id="ped90" depart="2790.00" departPos="random">
        <walk from="NC" to="CS" arrivalPos="random"/>
    </person>
    <person id="ped91" depart="2836.00" departPos="random">
        <walk from="NC" to="CS" arrivalPos="random"/>
    </person>
    <person id="ped92" depart="2874.00" departPos="random">
        <walk from="CS" to="NC" arrivalPos="random"/>
    </person>
    <person id="ped93" depart="3042.00" departPos="random">
        <walk from="NC" to="CS" arrivalPos="random"/>
    </person>
    <person id="ped94" depart="3058.00" departPos="random">
        <walk from="CS" to="NC" arrivalPos="random"/>
    </person>
    <person id="ped95" depart="3059.00" departPos="random">
        <walk from="CS" to="NC" arrivalPos="random"/>
    </person>
    <person id="ped96" depart="3065.00" departPos="random">
        <walk from="NC" to="CS" arrivalPos="random"/>
    </person>
    <person id="ped97" depart="3081.00" departPos="random">
        <walk from="NC" to="CS" arrivalPos="random"/>
    </person>
    <person id="ped98" depart="3088.00" departPos="random">
        <walk from="NC" to="CS" arrivalPos="random"/>
    </person>
    <person id="ped99" depart="3106.00" departPos="random">
        <walk from="CS" to="NC" arrivalPos="random"/>
    </person>
    <person id="ped100" depart="3128.00" departPos="random">
        <walk from="CS" to="NC" arrivalPos="random"/>
    </person>
    <person id="ped101" depart="3163.00" departPos="random">
        <walk from="NC" to="CS" arrivalPos="random"/>
    </person>
    <person id="ped102" depart="3186.00" departPos="random">
        <walk from="NC" to="CS" arrivalPos="random"/>
    </person>
    <person id="ped103" depart="3191.00" departPos="random">
        <walk from="NC" to="CS" arrivalPos="random"/>
    </person>
    <person id="ped104" depart="3198.00" departPos="random">
        <walk from="CS" to="NC" arrivalPos="random"/>
    </person>
    <person id="ped105" depart="3215.00" departPos="random">
        <walk from="CS" to="NC" arrivalPos="random"/>
    </person>
    <person id="ped106" depart="3299.00" departPos="random">
        <walk from="NC" to="CS" arrivalPos="random"/>
    </person>
    <person id="ped107" depart="3313.00" departPos="random">
        <walk from="CS" to="NC" arrivalPos="random"/>
    </person>
    <person id="ped108" depart="3343.00" departPos="random">
        <walk from="CS" to="NC" arrivalPos="random"/>
    </person>
    <person id="ped109" depart="3361.00" departPos="random">
        <walk from="NC" to="CS" arrivalPos="random"/>
    </person>
    <person id="ped110" depart="3389.00" departPos="random">
        <walk from="CS" to="NC" arrivalPos="random"/>
    </person>
    <person id="ped111" depart="3457.00" departPos="random">
        <walk from="NC" to="CS" arrivalPos="random"/>
    </person>
    <person id="ped112" depart="3510.00" departPos="random">
        <walk from="CS" to="NC" arrivalPos="random"/>
    </person>
    <person id="ped113" depart="3572.00" departPos="random">
        <walk from="CS" to="NC" arrivalPos="random"/>
    </person>
    <person id="ped114" depart="3576.00" departPos="random">
        <walk from="CS" to="NC" arrivalPos="random"/>
    </person>
</routes>
